examples/__init__.py
examples/access_mongodb.py
examples/smbo.py
examples/test_db_object.py
litebo/__init__.py
litebo/__main__.py
litebo/pkginfo.py
litebo/acq_maximizer/__init__.py
litebo/acq_maximizer/ei_optimization.py
litebo/acq_maximizer/random_configuration_chooser.py
litebo/acquisition_function/__init__.py
litebo/acquisition_function/acquisition.py
litebo/acquisition_function/mc_acquisition.py
litebo/acquisition_function/mc_multi_objective_acquisition.py
litebo/acquisition_function/multi_objective_acquisition.py
litebo/apps/__init__.py
litebo/apps/multi_fidelity/__init__.py
litebo/apps/multi_fidelity/async_mq_base_facade.py
litebo/apps/multi_fidelity/async_mq_hb.py
litebo/apps/multi_fidelity/async_mq_mf_worker.py
litebo/apps/multi_fidelity/async_mq_mfes.py
litebo/apps/multi_fidelity/async_mq_sh.py
litebo/apps/multi_fidelity/mq_base_facade.py
litebo/apps/multi_fidelity/mq_bohb.py
litebo/apps/multi_fidelity/mq_hb.py
litebo/apps/multi_fidelity/mq_mf_worker.py
litebo/apps/multi_fidelity/mq_mfes.py
litebo/apps/multi_fidelity/mq_random_search.py
litebo/apps/multi_fidelity/utils.py
litebo/artifact/__init__.py
litebo/artifact/manage.py
litebo/artifact/remote_advisor.py
litebo/artifact/artifact/__init__.py
litebo/artifact/artifact/asgi.py
litebo/artifact/artifact/settings.py
litebo/artifact/artifact/test_task_done.py
litebo/artifact/artifact/test_task_register.py
litebo/artifact/artifact/urls.py
litebo/artifact/artifact/wsgi.py
litebo/artifact/bo_advice/__init__.py
litebo/artifact/bo_advice/admin.py
litebo/artifact/bo_advice/apps.py
litebo/artifact/bo_advice/models.py
litebo/artifact/bo_advice/tests.py
litebo/artifact/bo_advice/urls.py
litebo/artifact/bo_advice/views.py
litebo/artifact/bo_advice/migrations/0001_initial.py
litebo/artifact/bo_advice/migrations/__init__.py
litebo/artifact/data_manipulation/__init__.py
litebo/artifact/data_manipulation/db_manipulator.py
litebo/artifact/data_manipulation/db_object.py
litebo/artifact/user_board/__init__.py
lite_bo-0.6.6.dist-info/LICENSE
lite_bo-0.6.6.dist-info/METADATA
lite_bo-0.6.6.dist-info/WHEEL
lite_bo-0.6.6.dist-info/entry_points.txt
lite_bo-0.6.6.dist-info/top_level.txt
lite_bo-0.6.6.dist-info/RECORD
