Metadata-Version: 2.1
Name: lite-bo
Version: 0.6.6
Summary: Efficient and generalized blackbox optimization (BBO) system
Home-page: https://github.com/thomas-young-2013/lite-bo
Author: Thomas (Yang) Li from DAIM@PKU
License: MIT
Platform: UNKNOWN
Requires-Python: >=3.5.2
Requires-Dist: dill
Requires-Dist: cython
Requires-Dist: psutil
Requires-Dist: setuptools
Requires-Dist: requests
Requires-Dist: statsmodels
Requires-Dist: pyyaml
Requires-Dist: lazy-import
Requires-Dist: scikit-optimize
Requires-Dist: emcee
Requires-Dist: tqdm
Requires-Dist: terminaltables
Requires-Dist: matplotlib
Requires-Dist: scipy (>=0.18.1)
Requires-Dist: platypus-opt (==1.0.4)
Requires-Dist: pyrfr (>=0.5.0)
Requires-Dist: numpy (>=1.7.1)
Requires-Dist: ConfigSpace (<0.5,>=0.4.6)
Requires-Dist: scikit-learn (==0.21.3)
Requires-Dist: tensorboardX
Requires-Dist: django (>=2.2.17)
Requires-Dist: Pyro4
Provides-Extra: dev
Requires-Dist: pytest ; extra == 'dev'
Requires-Dist: mypy ; extra == 'dev'
Requires-Dist: ipykernel ; extra == 'dev'
Requires-Dist: wheel ; extra == 'dev'
Requires-Dist: selenium ; extra == 'dev'
Requires-Dist: sphinx ; extra == 'dev'
Requires-Dist: twine ; extra == 'dev'
Requires-Dist: guzzle-sphinx-theme ; extra == 'dev'
Requires-Dist: pre-commit ; extra == 'dev'
Requires-Dist: pandas ; extra == 'dev'
Requires-Dist: streamlit (>=0.63) ; extra == 'dev'
Requires-Dist: beautifulsoup4 ; extra == 'dev'
